lab1/chip_7458.v
module chip_7458 ( // Описание модуля, реализующего логику И-НЕ 7458
    p1a, p1b, p1c, p1d, p1e, p1f, // Входы первой группы (две тройки для двух 3-входовых И)
    p1y, // Выход первой группы (ИЛИ из двух 3-входовых И)
    p2a, p2b, p2c, p2d, // Входы второй группы (две пары для двух 2-входовых И)
    p2y ); // Выход второй группы (ИЛИ из двух 2-входовых И)

input p1a, p1b, p1c, p1d, p1e, p1f; // Объявление входов первой группы
input p2a, p2b, p2c, p2d; // Объявление входов второй группы
output p1y; // Объявление выхода первой группы
output p2y; // Объявление выхода второй группы

assign p1y = (p1a & p1b & p1c) | (p1d & p1e & p1f); // Первая функция: (A&B&C) OR (D&E&F)
assign p2y = (p2a & p2b) | (p2c & p2d); // Вторая функция: (A&B) OR (C&D)

endmodule // Конец описания модуля

lab1/chip_7458_tb.v
`timescale 1ns/100ps // 1 ns time unit, 100 ps resolution
`include "chip_7458.v"

module chip_7458_tb;

	reg p1a = 0,p1b = 0,p1c = 0,p1d = 0,p1e = 0,p1f = 0;
	reg p2a = 0,p2b = 0,p2c = 0,p2d = 0;
	reg[15:0] time_of_err;
	wire p1y, p2y;
	wire mismatch;
	

	reg p1y_compare = 0, p2y_compare = 0;
	reg isErr;

	chip_7458 chip_7458_mod0
	(
		.p1a(p1a),
		.p1b(p1b),
		.p1c(p1c),
		.p1d(p1d),
		.p1e(p1e),
		.p1f(p1f),
		.p2a(p2a),
		.p2b(p2b),
		.p2c(p2c),
		.p2d(p2d),
		.p1y(p1y),
		.p2y(p2y)
	);

	event gen_result;

	assign mismatch = (p1y ^ p1y_compare) || (p2y ^ p2y_compare);

	initial begin
		$dumpfile("wave.vcd");		// create a VCD waveform dump called "wave.vcd"
		$dumpvars(0, chip_7458_tb);		// dump variable changes in the testbench
									// and all modules under it
		isErr = 0; time_of_err = 16'bx;



		#5;p1a=0; p1b=0; p1c=0; p1d=0; p1e=0; p1f=0; p2a=0; p2b=0; p2c=0; p2d=0; p1y_compare = 0; p2y_compare = 0;
		#5;p1a=0; p1b=0; p1c=0; p1d=0; p1e=0; p1f=0; p2a=0; p2b=0; p2c=0; p2d=0; p1y_compare = 0; p2y_compare = 0;
		#5;p1a=0; p1b=0; p1c=1; p1d=0; p1e=0; p1f=0; p2a=0; p2b=0; p2c=0; p2d=1; p1y_compare = 0; p2y_compare = 0;
		#5;p1a=0; p1b=1; p1c=0; p1d=0; p1e=0; p1f=1; p2a=0; p2b=0; p2c=1; p2d=0; p1y_compare = 0; p2y_compare = 0;
		#5;p1a=0; p1b=1; p1c=1; p1d=0; p1e=0; p1f=1; p2a=0; p2b=0; p2c=1; p2d=1; p1y_compare = 0; p2y_compare = 1;
		#5;p1a=0; p1b=0; p1c=0; p1d=0; p1e=0; p1f=0; p2a=0; p2b=1; p2c=0; p2d=0; p1y_compare = 0; p2y_compare = 0;
		#5;p1a=1; p1b=0; p1c=1; p1d=0; p1e=1; p1f=0; p2a=0; p2b=1; p2c=0; p2d=1; p1y_compare = 0; p2y_compare = 0;
		#5;p1a=1; p1b=1; p1c=0; p1d=0; p1e=1; p1f=1; p2a=0; p2b=1; p2c=1; p2d=0; p1y_compare = 0; p2y_compare = 0;
		#5;p1a=1; p1b=1; p1c=1; p1d=0; p1e=1; p1f=1; p2a=0; p2b=1; p2c=1; p2d=1; p1y_compare = 1; p2y_compare = 1;
		#5;p1a=1; p1b=0; p1c=0; p1d=1; p1e=1; p1f=0; p2a=1; p2b=0; p2c=0; p2d=0; p1y_compare = 0; p2y_compare = 0;
		#5;p1a=0; p1b=0; p1c=1; p1d=1; p1e=0; p1f=0; p2a=1; p2b=0; p2c=0; p2d=1; p1y_compare = 0; p2y_compare = 0;
		#5;p1a=0; p1b=1; p1c=0; p1d=1; p1e=0; p1f=1; p2a=1; p2b=0; p2c=1; p2d=0; p1y_compare = 0; p2y_compare = 0;
		#5;p1a=0; p1b=1; p1c=1; p1d=1; p1e=0; p1f=1; p2a=1; p2b=0; p2c=1; p2d=1; p1y_compare = 0; p2y_compare = 1;
		#5;p1a=0; p1b=0; p1c=0; p1d=1; p1e=0; p1f=0; p2a=1; p2b=1; p2c=0; p2d=0; p1y_compare = 0; p2y_compare = 1;
		#5;p1a=1; p1b=0; p1c=1; p1d=1; p1e=1; p1f=0; p2a=1; p2b=1; p2c=0; p2d=1; p1y_compare = 0; p2y_compare = 1;
		#5;p1a=1; p1b=1; p1c=0; p1d=1; p1e=1; p1f=1; p2a=1; p2b=1; p2c=1; p2d=0; p1y_compare = 1; p2y_compare = 1;
		#5;p1a=1; p1b=1; p1c=1; p1d=1; p1e=1; p1f=1; p2a=1; p2b=1; p2c=1; p2d=1; p1y_compare = 1; p2y_compare = 1;
		#5;p1a=1; p1b=0; p1c=0; p1d=0; p1e=1; p1f=0; p2a=0; p2b=0; p2c=0; p2d=0; p1y_compare = 0; p2y_compare = 0;
		#5;p1a=0; p1b=0; p1c=1; p1d=0; p1e=0; p1f=0; p2a=0; p2b=0; p2c=0; p2d=1; p1y_compare = 0; p2y_compare = 0;
		#5;p1a=0; p1b=1; p1c=0; p1d=0; p1e=0; p1f=1; p2a=0; p2b=0; p2c=1; p2d=0; p1y_compare = 0; p2y_compare = 0;
		#5;p1a=0; p1b=1; p1c=1; p1d=0; p1e=0; p1f=1; p2a=0; p2b=0; p2c=1; p2d=1; p1y_compare = 0; p2y_compare = 1;
		#5;p1a=0; p1b=0; p1c=0; p1d=0; p1e=0; p1f=0; p2a=0; p2b=1; p2c=0; p2d=0; p1y_compare = 0; p2y_compare = 0;
		#5;p1a=1; p1b=0; p1c=1; p1d=0; p1e=1; p1f=0; p2a=0; p2b=1; p2c=0; p2d=1; p1y_compare = 0; p2y_compare = 0;
		#5;p1a=1; p1b=1; p1c=0; p1d=0; p1e=1; p1f=1; p2a=0; p2b=1; p2c=1; p2d=0; p1y_compare = 0; p2y_compare = 0;
		#5;p1a=1; p1b=1; p1c=1; p1d=0; p1e=1; p1f=1; p2a=0; p2b=1; p2c=1; p2d=1; p1y_compare = 1; p2y_compare = 1;
		#5 -> gen_result;

	end


	always @(*) begin
		if (p1y === 1'bz) begin
			isErr = 1;
			time_of_err = time_of_err === 16'bx ? $time : time_of_err;
			$display("p1y is in high-impedance (Z) state at t=%d", $time);
		end
		if (p1y === 1'bx) begin
			isErr = 1;
			time_of_err = time_of_err === 16'bx ? $time : time_of_err;
			$display("p1y is in unknown (X) state at t=%d", $time);
		end
	end


	always @ (posedge mismatch) begin
		if (((p1y ^ p1y_compare) || (p2y ^ p2y_compare))) begin
			isErr = 1;
			time_of_err = time_of_err === 16'bx ? $time : time_of_err;
		end
	end

	initial begin
		@ (gen_result) begin
			$display ("###################################################");

			if (isErr) begin
				$display("Result: FAIL");
				$display("First error at t=%-4d", time_of_err);
			end else
				$display("Result: PASS");
			$display ("###################################################");
			$finish;
		end
	end


	initial begin
		$monitor("t=%-4d: p1y = %d, p2y = %d", $time, p1y, p2y);
	end
endmodule

wave.vcd
$date
	Mon Sep 15 11:26:52 2025
$end
$version
	Icarus Verilog
$end
$timescale
	100ps
$end
$scope module chip_7458_tb $end
$var event 1 ! gen_result $end
$var wire 1 " mismatch $end
$var wire 1 # p2y $end
$var wire 1 $ p1y $end
$var reg 1 % isErr $end
$var reg 1 & p1a $end
$var reg 1 ' p1b $end
$var reg 1 ( p1c $end
$var reg 1 ) p1d $end
$var reg 1 * p1e $end
$var reg 1 + p1f $end
$var reg 1 , p1y_compare $end
$var reg 1 - p2a $end
$var reg 1 . p2b $end
$var reg 1 / p2c $end
$var reg 1 0 p2d $end
$var reg 1 1 p2y_compare $end
$var reg 16 2 time_of_err [15:0] $end
$scope module chip_7458_mod0 $end
$var wire 1 & p1a $end
$var wire 1 ' p1b $end
$var wire 1 ( p1c $end
$var wire 1 ) p1d $end
$var wire 1 * p1e $end
$var wire 1 + p1f $end
$var wire 1 $ p1y $end
$var wire 1 - p2a $end
$var wire 1 . p2b $end
$var wire 1 / p2c $end
$var wire 1 0 p2d $end
$var wire 1 # p2y $end
$upscope $end
$upscope $end
$enddefinitions $end
#0
$dumpvars
bx 2
01
00
0/
0.
0-
0,
0+
0*
0)
0(
0'
0&
0%
0$
0#
0"
1!
$end
#150
10
1(
#200
00
1/
1+
0(
1'
#250
0"
1#
11
10
1(
#300
0"
0#
01
00
0/
1.
0+
0(
0'
#350
10
1*
1(
1&
#400
00
1/
1+
0(
1'
#450
0"
1#
1$
11
1,
10
1(
#500
0"
0#
0$
01
0,
00
0/
0.
1-
0+
1)
0(
0'
#550
10
0*
1(
0&
#600
00
1/
1+
0(
1'
#650
0"
1#
11
10
1(
#700
00
0/
1.
0+
0(
0'
#750
10
1*
1(
1&
#800
0"
1$
1,
00
1/
1+
0(
1'
#850
10
1(
#900
0"
0#
0$
01
0,
00
0/
0.
0-
0+
0)
0(
0'
#950
10
0*
1(
0&
#1000
00
1/
1+
0(
1'
#1050
0"
1#
11
10
1(
#1100
0"
0#
01
00
0/
1.
0+
0(
0'
#1150
10
1*
1(
1&
#1200
00
1/
1+
0(
1'
#1250
0"
1#
1$
11
1,
10
1(
#1300
1!
