lab1/part_5_top_module.v
module part_5_top_module (input [31:0]a, input [31:0]b, input sub, output [31:0] sum); // Сложение/вычитание на одном сумматоре

    wire [31:0] b_xor; // Модифицированный операнд b
    wire cin; // Входной перенос (для вычитания = 1)

    assign b_xor = b ^ {32{sub}}; // Если sub=1, инвертируем b (доп. код), иначе оставляем как есть
    assign cin = sub;             // При вычитании добавляем 1: a + (~b) + 1

    assign sum = a + b_xor + cin; // Универсальная операция: сложение или вычитание

endmodule

lab1/part_5_add_tb.v
`timescale 1ns/100ps // 1 ns time unit, 100 ps resolution
`include "part_5_top_module.v"

module part_5_top_tb;
	reg [31:0]a = 0,b = 0;
	reg sub = 0;
	wire [31:0]sum;

	reg[15:0] time_of_err = 16'bx;
	wire mismatch;

	reg[31:0] sum_compare = 0;
	reg isErr = 0;

	event gen_result;

	assign mismatch = (sum != sum_compare);

	part_5_top_module top0
	(
		.a(a),
		.b(b),
		.sub(sub),
		.sum(sum)
	);


	initial begin
		$dumpfile("wave.vcd");		// create a VCD waveform dump called "wave.vcd"
		$dumpvars(0, part_5_top_tb);		// dump variable changes in the testbench
									// and all modules under it
		
		#5 a = 1; b = 0; sum_compare = 1;
		#5 a = 2; sum_compare = 2;
		#5 b = 1; sub = 1; sum_compare = 1;
		#5 b = 2; sum_compare = 0;
		#5 a = 32'hffff; b = 1; sub = 0; sum_compare = 32'h10000;
		#5 a = 32'h10000; sub = 1; sum_compare = 32'hffff;
		#5 a = 32'hffff_ffff; b = 32'hffff_ffff; sub = 0; sum_compare = 32'hfffffffe;
		#5 -> gen_result;
	
	end

	always @(*) begin
		if (sum === 32'bz) begin
			isErr = 1;
			time_of_err = time_of_err === 16'bx ? $time : time_of_err;
			$display("p1y is in high-impedance (Z) state at t=%d", $time);
		end
		if (sum === 32'bx) begin
			isErr = 1;
			time_of_err = time_of_err === 16'bx ? $time : time_of_err;
			$display("p1y is in unknown (X) state at t=%d", $time);
		end
	end

	always @ (posedge mismatch) begin
		#0.1
		if (sum != sum_compare) begin
			isErr = 1;
			time_of_err = time_of_err === 16'bx ? $time : time_of_err;
		end
	end

	initial begin
		@ (gen_result) begin
			$display ("###################################################");

			if (isErr) begin
				$display("Result: FAIL");
				$display("First error at t=%-4d", time_of_err);
			end else
				$display("Result: PASS");
			$display ("###################################################");
			$finish;
		end
	end

	initial begin
		$monitor("t=%-4d: a = %h, b = %h, sub = %h, s = %h", $time, a, b, sub,sum);
	end
endmodule

lab1/build/wave.vcd
$date
	Mon Sep 15 13:02:34 2025
$end
$version
	Icarus Verilog
$end
$timescale
	100ps
$end
$scope module part_5_top_tb $end
$var event 1 ! gen_result $end
$var wire 32 " sum [31:0] $end
$var wire 1 # mismatch $end
$var reg 32 $ a [31:0] $end
$var reg 32 % b [31:0] $end
$var reg 1 & isErr $end
$var reg 1 ' sub $end
$var reg 32 ( sum_compare [31:0] $end
$var reg 16 ) time_of_err [15:0] $end
$scope module top0 $end
$var wire 32 * a [31:0] $end
$var wire 32 + b [31:0] $end
$var wire 32 , b_xor [31:0] $end
$var wire 1 - cin $end
$var wire 1 ' sub $end
$var wire 32 . sum [31:0] $end
$upscope $end
$upscope $end
$enddefinitions $end
#0
$dumpvars
b0 .
0-
b0 ,
b0 +
b0 *
bx )
b0 (
0'
0&
b0 %
b0 $
0#
b0 "
1!
$end
#50
b1 (
0#
b1 "
b1 .
b1 $
b1 *
#100
b10 (
0#
b10 "
b10 .
b10 $
b10 *
#150
b11111111111111111111111111111110 ,
b1 (
0#
b1 "
b1 .
1-
1'
b1 %
b1 +
#200
b0 "
b0 .
b11111111111111111111111111111101 ,
0#
b0 (
b10 %
b10 +
#250
b1 ,
b10000000000000000 (
0-
0'
b1 %
b1 +
0#
b10000000000000000 "
b10000000000000000 .
b1111111111111111 $
b1111111111111111 *
#300
b11111111111111111111111111111110 ,
b1111111111111111 (
1-
1'
0#
b1111111111111111 "
b1111111111111111 .
b10000000000000000 $
b10000000000000000 *
#350
b11111111111111111111111111111111 ,
b11111111111111111111111111111110 (
0-
0'
b11111111111111111111111111111111 %
b11111111111111111111111111111111 +
0#
b11111111111111111111111111111110 "
b11111111111111111111111111111110 .
b11111111111111111111111111111111 $
b11111111111111111111111111111111 *
#400
1!
