lab1/part_3_top_module.v
module part_3_top_module (input [31:0]a, input [31:0]b, input cin, output [31:0] sum); // 32-битный сумматор из двух 16-битных блоков

    wire [15:0] low_sum; // Сумма младших 16 бит
    wire [15:0] high_sum; // Сумма старших 16 бит
    wire carry16; // Перенос из младших 16 бит
    wire carry32; // Перенос из старших 16 бит (не используется дальше)

    // Нижняя часть: складываем младшие 16 бит
    assign {carry16, low_sum} = a[15:0] + b[15:0];

    // Верхняя часть: складываем старшие 16 бит с переносом carry16
    assign {carry32, high_sum} = a[31:16] + b[31:16] + carry16;

    assign sum = {high_sum, low_sum}; // Собираем 32-битную сумму

endmodule // Конец модуля part_3_top_module

lab1/part_3_add_tb.v
`timescale 1ns/100ps // 1 ns time unit, 100 ps resolution
`include "part_3_top_module.v"

module part_3_top_tb;
	reg [31:0]a = 0,b = 0;
	wire [31:0]sum;

	reg[15:0] time_of_err = 16'bx;
	wire mismatch;

	reg[31:0] sum_compare = 0;
	reg isErr = 0;

	event gen_result;

	assign mismatch = (sum != sum_compare);

	part_3_top_module top0
	(
		.a(a),
		.b(b),
		.sum(sum)
	);


	initial begin
		$dumpfile("wave.vcd");		// create a VCD waveform dump called "wave.vcd"
		$dumpvars(0, part_3_top_tb);		// dump variable changes in the testbench
									// and all modules under it
		
		#5 a = 0; b = 1; sum_compare = 1;
		#5 b = 2; sum_compare = 2;
		#5 a = 1; sum_compare = 3;
		#5 a = 32'hffff; b = 0; sum_compare = 32'hffff;
		#5 b = 1; sum_compare = 32'h10000;
		#5 b = 32'h2ccc1; sum_compare = 32'h3ccc0;
		#5 -> gen_result;
	
		
	end


	always @(*) begin
		if (sum === 32'bz) begin
			isErr = 1;
			time_of_err = time_of_err === 16'bx ? $time : time_of_err;
			$display("p1y is in high-impedance (Z) state at t=%d", $time);
		end
		if (sum === 32'bx) begin
			isErr = 1;
			time_of_err = time_of_err === 16'bx ? $time : time_of_err;
			$display("p1y is in unknown (X) state at t=%d", $time);
		end
	end

	always @ (posedge mismatch) begin
		#0.1
		if (sum != sum_compare) begin
			isErr = 1;
			time_of_err = time_of_err === 16'bx ? $time : time_of_err;
		end
	end

	initial begin
		@ (gen_result) begin
			$display ("###################################################");

			if (isErr) begin
				$display("Result: FAIL");
				$display("First error at t=%-4d", time_of_err);
			end else
				$display("Result: PASS");
			$display ("###################################################");
			$finish;
		end
	end

	initial begin
		$monitor("t=%-4d: a = %h, b = %h, s = %h", $time, a, b,sum);
	end
endmodule

lab1/wave.vcd
$date
	Mon Sep 15 12:50:16 2025
$end
$version
	Icarus Verilog
$end
$timescale
	100ps
$end
$scope module part_3_top_tb $end
$var event 1 ! gen_result $end
$var wire 32 " sum [31:0] $end
$var wire 1 # mismatch $end
$var reg 32 $ a [31:0] $end
$var reg 32 % b [31:0] $end
$var reg 1 & isErr $end
$var reg 32 ' sum_compare [31:0] $end
$var reg 16 ( time_of_err [15:0] $end
$scope module top0 $end
$var wire 32 ) a [31:0] $end
$var wire 32 * b [31:0] $end
$var wire 1 + cin $end
$var wire 32 , sum [31:0] $end
$var wire 16 - low_sum [15:0] $end
$var wire 16 . high_sum [15:0] $end
$var wire 1 / carry32 $end
$var wire 1 0 carry16 $end
$upscope $end
$upscope $end
$enddefinitions $end
#0
$dumpvars
00
0/
b0 .
b0 -
b0 ,
z+
b0 *
b0 )
bx (
b0 '
0&
b0 %
b0 $
0#
b0 "
1!
$end
#50
b1 "
b1 ,
b1 -
0#
b1 '
b1 %
b1 *
#100
b10 "
b10 ,
b10 -
0#
b10 '
b10 %
b10 *
#150
b11 "
b11 ,
b11 -
0#
b11 '
b1 $
b1 )
#200
b1111111111111111 "
b1111111111111111 ,
b1111111111111111 -
0#
b1111111111111111 '
b0 %
b0 *
b1111111111111111 $
b1111111111111111 )
#250
b1 .
b10000000000000000 "
b10000000000000000 ,
b0 -
10
0#
b10000000000000000 '
b1 %
b1 *
#300
b1100110011000000 -
b111100110011000000 "
b111100110011000000 ,
b11 .
0#
b111100110011000000 '
b101100110011000001 %
b101100110011000001 *
#350
1!
